MANIFEST.in
README.md
setup.py
qiu_utils/__init__.py
qiu_utils.egg-info/PKG-INFO
qiu_utils.egg-info/SOURCES.txt
qiu_utils.egg-info/dependency_links.txt
qiu_utils.egg-info/top_level.txt
qiu_utils/db_utils/__init__.py
qiu_utils/db_utils/mongdb_utils.py
qiu_utils/db_utils/mysql_utls.py
qiu_utils/utils/__init__.py
qiu_utils/utils/file_utils.py
qiu_utils/utils/mutiprocess_utils.py
qiu_utils/utils/pinyin_utils.py
qiu_utils/utils/re_utils.py
qiu_utils/utils/snippets.py
qiu_utils/utils/text_utils.py
qiu_utils/utils/time_utils.py
qiu_utils/utils/tried_tree_utils.py
qiu_utils/utils/xpath_utils.py