Metadata-Version: 2.1
Name: qiu-utils
Version: 1.0.1
Summary: 工作中相关的一些定义以及一些常用函数封装
Home-page: UNKNOWN
Author: qiufengfeng
Author-email: 544855237@qq.com
License: LGPL
Platform: UNKNOWN
